astromodellinglib/__init__.py
astromodellinglib-1.1.dist-info/LICENSE.txt
astromodellinglib-1.1.dist-info/METADATA
astromodellinglib-1.1.dist-info/WHEEL
astromodellinglib-1.1.dist-info/top_level.txt
astromodellinglib-1.1.dist-info/RECORD
