Metadata-Version: 2.1
Name: astromodellinglib
Version: 1.1
Summary: Python scripts to modelling kinematics, dynamics and morphology of galaxies.
Home-page: https://gitlab.com/joseaher/astromodellinglib
Author: J. A. Hernandez-Jimenez
Author-email: joseaher@gmail.com
License-File: LICENSE.txt
